CHANGELOG
COPYRIGHT
INSTALL
LICENSE
MANIFEST.in
README
TODO
account_voucher_ar.xml
setup.py
tryton.cfg
./__init__.py
./account_voucher_ar.py
./account_voucher_ar.xml
./move.py
./tryton.cfg
./locale/es_AR.po
./tests/__init__.py
./tests/test_account_voucher_ar.py
./view/account_voucher_form.xml
./view/account_voucher_tree.xml
./view/lines_credits_tree.xml
./view/lines_debits_tree.xml
./view/lines_tree.xml
./view/pay_lines_tree.xml
locale/es_AR.po
trytonar_account_voucher_ar.egg-info/PKG-INFO
trytonar_account_voucher_ar.egg-info/SOURCES.txt
trytonar_account_voucher_ar.egg-info/dependency_links.txt
trytonar_account_voucher_ar.egg-info/entry_points.txt
trytonar_account_voucher_ar.egg-info/not-zip-safe
trytonar_account_voucher_ar.egg-info/requires.txt
trytonar_account_voucher_ar.egg-info/top_level.txt
view/account_voucher_form.xml
view/account_voucher_tree.xml
view/lines_credits_tree.xml
view/lines_debits_tree.xml
view/lines_tree.xml
view/pay_lines_tree.xml